talos_mcp/__init__.py
talos_mcp/cli.py
talos_mcp/handlers.py
talos_mcp/prompts.py
talos_mcp/py.typed
talos_mcp/registry.py
talos_mcp/resources.py
talos_mcp/server.py
talos_mcp/core/__init__.py
talos_mcp/core/client.py
talos_mcp/core/exceptions.py
talos_mcp/core/settings.py
talos_mcp/tools/__init__.py
talos_mcp/tools/base.py
talos_mcp/tools/cgroups.py
talos_mcp/tools/cluster.py
talos_mcp/tools/config.py
talos_mcp/tools/etcd.py
talos_mcp/tools/files.py
talos_mcp/tools/network.py
talos_mcp/tools/resources.py
talos_mcp/tools/services.py
talos_mcp/tools/support.py
talos_mcp/tools/system.py
talos_mcp/tools/volumes.py
talos_mcp_server-0.3.9.dist-info/METADATA
talos_mcp_server-0.3.9.dist-info/WHEEL
talos_mcp_server-0.3.9.dist-info/entry_points.txt
talos_mcp_server-0.3.9.dist-info/licenses/LICENSE
talos_mcp_server-0.3.9.dist-info/RECORD
