Metadata-Version: 2.4
Name: talos-mcp-server
Version: 0.3.9
Summary: MCP server for Talos Linux API integration - manage clusters with AI
Project-URL: Homepage, https://github.com/CBEPX/talos-mcp-server
Project-URL: Documentation, https://github.com/CBEPX/talos-mcp-server#readme
Project-URL: Repository, https://github.com/CBEPX/talos-mcp-server.git
Project-URL: Issues, https://github.com/CBEPX/talos-mcp-server/issues
Project-URL: Changelog, https://github.com/CBEPX/talos-mcp-server/blob/main/CHANGELOG.md
Author-email: Gleb Mekhrenin <mekhrenin@gmail.com>
Maintainer-email: Gleb Mekhrenin <mekhrenin@gmail.com>
License: MIT
License-File: LICENSE
Keywords: ai,claude,kubernetes,llm,mcp,model-context-protocol,talos,talosctl
Classifier: Development Status :: 4 - Beta
Classifier: Intended Audience :: Developers
Classifier: Intended Audience :: System Administrators
Classifier: License :: OSI Approved :: MIT License
Classifier: Operating System :: OS Independent
Classifier: Programming Language :: Python :: 3
Classifier: Programming Language :: Python :: 3.10
Classifier: Programming Language :: Python :: 3.11
Classifier: Programming Language :: Python :: 3.12
Classifier: Programming Language :: Python :: 3.13
Classifier: Topic :: Software Development :: Libraries :: Python Modules
Classifier: Topic :: System :: Systems Administration
Classifier: Typing :: Typed
Requires-Python: >=3.10
Requires-Dist: arrow>=1.3.0
Requires-Dist: betterproto>=2.0.0b6
Requires-Dist: grpclib>=0.4.7
Requires-Dist: loguru>=0.7.2
Requires-Dist: mcp>=1.0.0
Requires-Dist: pydantic-settings>=2.1.0
Requires-Dist: pydantic>=2.5.3
Requires-Dist: pyyaml>=6.0.2
Requires-Dist: tenacity>=8.2.3
Requires-Dist: typer>=0.9.0
Requires-Dist: uvloop>=0.19.0
Provides-Extra: dev
Requires-Dist: autopep8>=2.0.4; extra == 'dev'
Requires-Dist: bandit>=1.7.8; extra == 'dev'
Requires-Dist: black>=24.0.0; extra == 'dev'
Requires-Dist: mypy>=1.9.0; extra == 'dev'
Requires-Dist: pre-commit>=3.7.0; extra == 'dev'
Requires-Dist: prospector>=1.10.3; extra == 'dev'
Requires-Dist: pytest-asyncio>=0.23.0; extra == 'dev'
Requires-Dist: pytest-cov>=4.1.0; extra == 'dev'
Requires-Dist: pytest-mock>=3.12.0; extra == 'dev'
Requires-Dist: pytest-xdist>=3.5.0; extra == 'dev'
Requires-Dist: pytest>=8.0.0; extra == 'dev'
Requires-Dist: ruff>=0.4.0; extra == 'dev'
Requires-Dist: types-pyyaml>=6.0.12; extra == 'dev'
Requires-Dist: vulture>=2.11; extra == 'dev'
